agent_fuse/__init__.py
agent_fuse/config.py
agent_fuse/core/__init__.py
agent_fuse/core/circuit_breaker.py
agent_fuse/core/cost_tracker.py
agent_fuse/core/default_pricing.json
agent_fuse/core/exceptions.py
agent_fuse/core/loop_detector.py
agent_fuse/core/state_manager.py
agent_fuse/integrations/__init__.py
agent_fuse/integrations/langchain.py
agent_fuse/integrations/openai_shim.py
agent_fuse/storage/__init__.py
agent_fuse/storage/schema.sql
agent_fuse/storage/sqlite.py
agent_fuse/utils/__init__.py
agent_fuse/utils/token_heuristics.py
agent_fuse-0.2.1.dist-info/METADATA
agent_fuse-0.2.1.dist-info/WHEEL
agent_fuse-0.2.1.dist-info/licenses/LICENSE
agent_fuse-0.2.1.dist-info/RECORD
