Metadata-Version: 2.4
Name: agent-fuse
Version: 0.2.1
Summary: A Circuit Breaker for AI Agents - Fail Safe by Default
Project-URL: Homepage, https://github.com/agentfuse/agent-fuse
Project-URL: Documentation, https://github.com/agentfuse/agent-fuse#readme
Project-URL: Repository, https://github.com/agentfuse/agent-fuse
Author: AgentFuse Team
License-Expression: MIT
License-File: LICENSE
Keywords: agents,ai,circuit-breaker,langchain,llm,openai,safety
Classifier: Development Status :: 3 - Alpha
Classifier: Intended Audience :: Developers
Classifier: License :: OSI Approved :: MIT License
Classifier: Programming Language :: Python :: 3
Classifier: Programming Language :: Python :: 3.10
Classifier: Programming Language :: Python :: 3.11
Classifier: Programming Language :: Python :: 3.12
Classifier: Topic :: Software Development :: Libraries :: Python Modules
Requires-Python: >=3.10
Requires-Dist: pydantic-settings>=2.0
Requires-Dist: pydantic>=2.0
Provides-Extra: all
Requires-Dist: langchain-core>=0.1; extra == 'all'
Requires-Dist: openai>=1.0; extra == 'all'
Requires-Dist: tiktoken>=0.5; extra == 'all'
Provides-Extra: dev
Requires-Dist: mypy>=1.0; extra == 'dev'
Requires-Dist: pytest-asyncio>=0.21; extra == 'dev'
Requires-Dist: pytest-cov>=4.0; extra == 'dev'
Requires-Dist: pytest>=7.0; extra == 'dev'
Requires-Dist: ruff>=0.1; extra == 'dev'
Provides-Extra: langchain
Requires-Dist: langchain-core>=0.1; extra == 'langchain'
Provides-Extra: openai
Requires-Dist: openai>=1.0; extra == 'openai'
Provides-Extra: tiktoken
Requires-Dist: tiktoken>=0.5; extra == 'tiktoken'
